CHANGES.txt
LICENSE.txt
README.txt
ez_setup.py
setup.cfg
setup.py
Mappa.egg-info/PKG-INFO
Mappa.egg-info/SOURCES.txt
Mappa.egg-info/dependency_links.txt
Mappa.egg-info/entry_points.txt
Mappa.egg-info/not-zip-safe
Mappa.egg-info/requires.txt
Mappa.egg-info/top_level.txt
mappa/__init__.py
mappa/_meta.py
mappa/_proto.py
mappa/interfaces.py
mappa/miohandler.py
mappa/predicates.py
mappa/utils.py
mappa/xtm1utils.py
mappa/_internal/__init__.py
mappa/_internal/atomification.py
mappa/_internal/axis.py
mappa/_internal/constraints.py
mappa/_internal/dupremoval.py
mappa/_internal/enhancer.py
mappa/_internal/exceptions.py
mappa/_internal/filter.py
mappa/_internal/ft.py
mappa/_internal/helper.py
mappa/_internal/idgen.py
mappa/_internal/implhelper.py
mappa/_internal/it.py
mappa/_internal/itemexpr.py
mappa/_internal/kind.py
mappa/_internal/lit.py
mappa/_internal/mergeutils.py
mappa/_internal/op.py
mappa/_internal/siggen.py
mappa/backend/__init__.py
mappa/backend/event.py
mappa/backend/evtmultiplier.py
mappa/backend/identityman.py
mappa/backend/stub.py
mappa/backend/mem/__init__.py
mappa/backend/mem/index.py
mappa/backend/mem/model.py
mappa/writer/__init__.py
mappa/writer/interfaces.py
mappa/writer/xmlutils.py
mappa/writer/cxtm/__init__.py
mappa/writer/cxtm/cxtm10.py
mappa/writer/jtm/__init__.py
mappa/writer/jtm/_json.py
mappa/writer/jtm/jtm10.py
mappa/writer/xtm/__init__.py
mappa/writer/xtm/xtm10.py
mappa/writer/xtm/xtm20.py